MANIFEST.in
README.md
TODO.md
requirements.txt
setup.py
django_metrics/__init__.py
django_metrics/settings.py
django_metrics/urls.py
django_metrics/wsgi.py
django_metrics.egg-info/PKG-INFO
django_metrics.egg-info/SOURCES.txt
django_metrics.egg-info/dependency_links.txt
django_metrics.egg-info/requires.txt
django_metrics.egg-info/top_level.txt
metrics/__init__.py
metrics/admin.py
metrics/models.py
metrics/migrations/0001_initial.py
metrics/migrations/__init__.py
metrics/templatetags/__init__.py
metrics/templatetags/metrics_tags.py