Metadata-Version: 1.1
Name: django-metrics
Version: 0.0.1
Summary: Basic Django app that provides an interface to add metrics code snippets from the Django admin.
Home-page: UNKNOWN
Author: Antoine Humeau
Author-email: humeau.antoine@gmail.com
License: WTFPL
Platform: UNKNOWN
Classifier: Programming Language :: Python
Classifier: Natural Language :: English
Classifier: Operating System :: OS Independent
